rwa_sdk/__init__.py
rwa_sdk/auth.py
rwa_sdk/client.py
rwa_sdk/exceptions.py
rwa_sdk/models.py
rwa_sdk/utils.py
rwa_sdk/endpoints/__init__.py
rwa_sdk/endpoints/analytics.py
rwa_sdk/endpoints/assets.py
rwa_sdk/endpoints/networks.py
rwa_sdk/endpoints/platforms.py
rwa_sdk/endpoints/search.py
rwa_sdk/endpoints/token_holders.py
rwa_sdk/endpoints/transactions.py
rwa_sdk/endpoints/users.py
rwa_sdk_qdf-0.1.0.dist-info/LICENSE
rwa_sdk_qdf-0.1.0.dist-info/METADATA
rwa_sdk_qdf-0.1.0.dist-info/WHEEL
rwa_sdk_qdf-0.1.0.dist-info/top_level.txt
rwa_sdk_qdf-0.1.0.dist-info/RECORD
