Metadata-Version: 2.1
Name: rwa-sdk-qdf
Version: 0.1.0
Summary: QuantDeFi.ai RWA SDK - Professional toolkit for tokenized asset data analysis | $297B+ tracked assets
Home-page: https://quantdefi.ai
Author: samthedataman
Author-email: 
License: MIT
Project-URL: Homepage, https://quantdefi.ai
Project-URL: Documentation, https://github.com/quantdefi/rwa-sdk-qdf#readme
Project-URL: Repository, https://github.com/quantdefi/rwa-sdk-qdf
Project-URL: Bug Tracker, https://github.com/quantdefi/rwa-sdk-qdf/issues
Project-URL: QuantDeFi Platform, https://quantdefi.ai
Keywords: rwa blockchain tokenization stablecoins treasuries api sdk defi crypto web3 real-world-assets
Classifier: Development Status :: 3 - Alpha
Classifier: Intended Audience :: Developers
Classifier: Intended Audience :: Financial and Insurance Industry
Classifier: Topic :: Software Development :: Libraries :: Python Modules
Classifier: Topic :: Office/Business :: Financial
Classifier: License :: OSI Approved :: MIT License
Classifier: Programming Language :: Python :: 3
Classifier: Programming Language :: Python :: 3.8
Classifier: Programming Language :: Python :: 3.9
Classifier: Programming Language :: Python :: 3.10
Classifier: Programming Language :: Python :: 3.11
Classifier: Programming Language :: Python :: 3.12
Classifier: Operating System :: OS Independent
Requires-Python: >=3.8
License-File: LICENSE
Requires-Dist: aiohttp >=3.8.0
Requires-Dist: requests >=2.28.0
Provides-Extra: dev
Requires-Dist: pytest >=7.0.0 ; extra == 'dev'
Requires-Dist: pytest-asyncio >=0.21.0 ; extra == 'dev'
Requires-Dist: black >=23.0.0 ; extra == 'dev'
Requires-Dist: mypy >=1.0.0 ; extra == 'dev'
Requires-Dist: flake8 >=6.0.0 ; extra == 'dev'
Requires-Dist: twine >=4.0.0 ; extra == 'dev'
Requires-Dist: wheel >=0.38.0 ; extra == 'dev'
Requires-Dist: build >=0.10.0 ; extra == 'dev'
Provides-Extra: docs
Requires-Dist: sphinx >=5.0.0 ; extra == 'docs'
Requires-Dist: sphinx-rtd-theme >=1.2.0 ; extra == 'docs'
